Metadata-Version: 1.1
Name: affinitic.tools
Version: 1.0
Summary: Bunch of python tools
Home-page: https://github.com/affinitic/affinitic.tools
Author: Affinitic
Author-email: info@affinitic.be
License: GPL
Keywords: affinitic tools
Platform: UNKNOWN
Classifier: Environment :: Web Environment
Classifier: Programming Language :: Python
Classifier: Topic :: Software Development :: Libraries :: Python Modules
